testdata/__init__.py
testdata/__main__.py
testdata/base.py
testdata/client.py
testdata/compat.py
testdata/config.py
testdata/mocking.py
testdata/output.py
testdata/path.py
testdata/server.py
testdata/service.py
testdata/test.py
testdata/threading.py
testdata/user.py
testdata/data/__init__.py
testdata/data/animated.gif
testdata/data/countries.py
testdata/data/favicon.ico
testdata/data/static.gif
testdata/data/static.jpg
testdata/data/static.png
testdata/data/usa/__init__.py
testdata/data/usa/cities.py
testdata/data/usa/states.py
testdata/data/usa/zipcodes.py
testdata/types/__init__.py
testdata/types/datetime.py
testdata/types/mapping.py
testdata/types/number.py
testdata/types/sequence.py
testdata/types/string.py
testdata-7.3.1.dist-info/licenses/LICENSE.txt
testdata-7.3.1.dist-info/METADATA
testdata-7.3.1.dist-info/WHEEL
testdata-7.3.1.dist-info/entry_points.txt
testdata-7.3.1.dist-info/top_level.txt
testdata-7.3.1.dist-info/RECORD
