Metadata-Version: 2.4
Name: testdata
Version: 7.3.1
Summary: Easily generate random unicode test data among other things
Author-email: Jay Marcyes <jay@marcyes.com>
License-Expression: MIT
Project-URL: Homepage, https://github.com/Jaymon/testdata
Project-URL: Repository, https://github.com/Jaymon/testdata
Classifier: Development Status :: 5 - Production/Stable
Classifier: Environment :: Plugins
Classifier: Intended Audience :: Developers
Classifier: Operating System :: OS Independent
Classifier: Topic :: Software Development :: Testing
Classifier: Programming Language :: Python :: 3
Requires-Python: >=3.10
License-File: LICENSE.txt
Requires-Dist: datatypes
Dynamic: license-file
